Workbook

Sheet Residential Property
A1: Year | B1: Start of Year Price | C1: End of Year Price | D1: Income Yield % | E1: Total Return % | F1: Cumulative $ | G1: Notes
A2: 2013 | B2: 100 | C2: 103.5 | D2: 0.035 | E2: =(C2-B2)/B2+D2 -> 0.07 | F2: =1000*(1+E2) -> 1070 | G2: Income yield is assumed at 3.5% based on typical gross rental yields for residential property in major Australian cities
A3: 2014 | B3: 103.5 | C3: 107 | D3: 0.035 | E3: =(C3-B3)/B3+D3 -> 0.068816425 | F3: =F2*(1+E3) -> 1143.6336 | G3: Income yield is added because property investors earn returns from both price growth and rental income
A4: 2015 | B4: 107 | C4: 110.5 | D4: 0.035 | E4: =(C4-B4)/B4+D4 -> 0.06771028 | F4: =F3*(1+E4) -> 1221.0693
A5: 2016 | B5: 110.5 | C5: 114 | D5: 0.035 | E5: =(C5-B5)/B5+D5 -> 0.066674208 | F5: =F4*(1+E5) -> 1302.4832
A6: 2017 | B6: 114 | C6: 118 | D6: 0.035 | E6: =(C6-B6)/B6+D6 -> 0.070087719 | F6: =F5*(1+E6) -> 1393.7712
A7: 2018 | B7: 118 | C7: 120 | D7: 0.035 | E7: =(C7-B7)/B7+D7 -> 0.051949153 | F7: =F6*(1+E7) -> 1466.1765
A8: 2019 | B8: 120 | C8: 124 | D8: 0.035 | E8: =(C8-B8)/B8+D8 -> 0.068333333 | F8: =F7*(1+E8) -> 1566.3652
A9: 2020 | B9: 124 | C9: 128.5 | D9: 0.035 | E9: =(C9-B9)/B9+D9 -> 0.071290323 | F9: =F8*(1+E9) -> 1678.0319
A10: 2021 | B10: 128.5 | C10: 135 | D10: 0.035 | E10: =(C10-B10)/B10+D10 -> 0.085583658 | F10: =F9*(1+E10) -> 1821.644
A11: 2022 | B11: 135 | C11: 138 | D11: 0.035 | E11: =(C11-B11)/B11+D11 -> 0.057222222 | F11: =F10*(1+E11) -> 1925.8825
A12: 2023 | B12: 138 | C12: 142.5 | D12: 0.035 | E12: =(C12-B12)/B12+D12 -> 0.067608696 | F12: =F11*(1+E12) -> 2056.0889
A13: 2024 | B13: 142.5 | C13: 147 | D13: 0.035 | E13: =(C13-B13)/B13+D13 -> 0.066578947 | F13: =F12*(1+E13) -> 2192.9811

Sheet Commercial Office
A1: Year | B1: Start of Year Price | C1: End of Year Price | D1: Divdends | E1: Income Yield % | F1: Total Return % | G1: Cumulative $ | H1: Notes
A2: 2013 | B2: 7.5 | C2: 7.8 | D2: 0.37 | E2: =D2/B2 -> 0.049333333 | F2: =(C2-B2+D2)/B2 -> 0.089333333 | G2: =1000*(1+F2) -> 1089.3333 | H2: Dividend was estimated by dividing reported dividends paid by the number of shares outstanding, using Yahoo Finance data
A3: 2014 | B3: 7.8 | C3: 8.1 | D3: 0.39 | E3: =D3/B3 -> 0.05 | F3: =(C3-B3+D3)/B3 -> 0.088461538 | G3: =G2*(1+F3) -> 1185.6974
A4: 2015 | B4: 8.1 | C4: 8.4 | D4: 0.44 | E4: =D4/B4 -> 0.054320988 | F4: =(C4-B4+D4)/B4 -> 0.091358025 | G4: =G3*(1+F4) -> 1294.0204
A5: 2016 | B5: 8.4 | C5: 8.7 | D5: 0.42 | E5: =D5/B5 -> 0.05 | F5: =(C5-B5+D5)/B5 -> 0.085714286 | G5: =G4*(1+F5) -> 1404.9364
A6: 2017 | B6: 8.7 | C6: 9 | D6: 0.47 | E6: =D6/B6 -> 0.054022989 | F6: =(C6-B6+D6)/B6 -> 0.088505747 | G6: =G5*(1+F6) -> 1529.2814
A7: 2018 | B7: 9 | C7: 9.3 | D7: 0.51 | E7: =D7/B7 -> 0.056666667 | F7: =(C7-B7+D7)/B7 -> 0.09 | G7: =G6*(1+F7) -> 1666.9167
A8: 2019 | B8: 9.3 | C8: 9.6 | D8: 0.5 | E8: =D8/B8 -> 0.053763441 | F8: =(C8-B8+D8)/B8 -> 0.086021505 | G8: =G7*(1+F8) -> 1810.3074
A9: 2020 | B9: 9.6 | C9: 9.9 | D9: 0.52 | E9: =D9/B9 -> 0.054166667 | F9: =(C9-B9+D9)/B9 -> 0.085416667 | G9: =G8*(1+F9) -> 1964.9378
A10: 2021 | B10: 9.9 | C10: 10.2 | D10: 0.51 | E10: =D10/B10 -> 0.051515152 | F10: =(C10-B10+D10)/B10 -> 0.081818182 | G10: =G9*(1+F10) -> 2125.7055
A11: 2022 | B11: 10.2 | C11: 10.5 | D11: 0.53 | E11: =D11/B11 -> 0.051960784 | F11: =(C11-B11+D11)/B11 -> 0.081372549 | G11: =G10*(1+F11) -> 2298.6795
A12: 2023 | B12: 10.5 | C12: 10.8 | D12: 0.5 | E12: =D12/B12 -> 0.047619048 | F12: =(C12-B12+D12)/B12 -> 0.076190476 | G12: =G11*(1+F12) -> 2473.817
A13: 2024 | B13: 10.8 | C13: 11.1 | D13: 0.48 | E13: =D13/B13 -> 0.044444444 | F13: =(C13-B13+D13)/B13 -> 0.072222222 | G13: =G12*(1+F13) -> 2652.4816

Sheet Industrial Warehouse
A1: Year | B1: Start of Year Price | C1: End of Year Price | D1: Divdends(the first half year) | E1: Divdends(the second half year) | F1: Income Yield % | G1: Total Return % | H1: Cumulative $ | I1: Notes
A2: 2013 | B2: 4.42 | C2: 4.79 | D2: 0.097 | E2: 0.1035 | F2: =(D2+E2)/B2 -> 0.045361991 | G2: =(C2-B2+D2+E2)/B2 -> 0.1290724 | H2: =1000*(1+G2) -> 1129.0724
A3: 2014 | B3: 4.78 | C3: 6.03 | D3: 0.1035 | E3: 0.111 | F3: =(D3+E3)/B3 -> 0.044874477 | G3: =(C3-B3+D3+E3)/B3 -> 0.30638075 | H3: =H2*(1+G3) -> 1474.9984
A4: 2015 | B4: 5.8 | C4: 6.42 | D4: 0.111 | E4: 0.119 | F4: =(D4+E4)/B4 -> 0.039655172 | G4: =(C4-B4+D4+E4)/B4 -> 0.14655172 | H4: =H3*(1+G4) -> 1691.162
A5: 2016 | B5: 6.28 | C5: 7.08 | D5: 0.121 | E5: 0.127 | F5: =(D5+E5)/B5 -> 0.039490446 | G5: =(C5-B5+D5+E5)/B5 -> 0.16687898 | H5: =H4*(1+G5) -> 1973.3814
A6: 2017 | B6: 7.21 | C6: 8.56 | D6: 0.132 | E6: 0.1375 | F6: =(D6+E6)/B6 -> 0.037378641 | G6: =(C6-B6+D6+E6)/B6 -> 0.22461859 | H6: =H5*(1+G6) -> 2416.6396
A7: 2018 | B7: 8.44 | C7: 9.64 | D7: 0.1425 | E7: 0.15 | F7: =(D7+E7)/B7 -> 0.034656398 | G7: =(C7-B7+D7+E7)/B7 -> 0.17683649 | H7: =H6*(1+G7) -> 2843.9896 | I7: For 2020–2024, dividends were estimated at 0.15 AUD/year based on consistent semi-annual distributions
A8: 2019 | B8: 9.65 | C8: 13.65 | D8: 0.15 | E8: 0.15 | F8: =(D8+E8)/B8 -> 0.031088083 | G8: =(C8-B8+D8+E8)/B8 -> 0.44559585 | H8: =H7*(1+G8) -> 4111.2596
A9: 2020 | B9: 13.44 | C9: 19.35 | D9: 0.15 | E9: 0.15 | F9: =(D9+E9)/B9 -> 0.022321429 | G9: =(C9-B9+D9+E9)/B9 -> 0.46205357 | H9: =H8*(1+G9) -> 6010.8818
A10: 2021 | B10: 19.36 | C10: 26.96 | D10: 0.15 | E10: 0.15 | F10: =(D10+E10)/B10 -> 0.015495868 | G10: =(C10-B10+D10+E10)/B10 -> 0.40805785 | H10: =H9*(1+G10) -> 8463.6693
A11: 2022 | B11: 26.76 | C11: 17.37 | D11: 0.15 | E11: 0.15 | F11: =(D11+E11)/B11 -> 0.011210762 | G11: =(C11-B11+D11+E11)/B11 -> -0.3396861 | H11: =H10*(1+G11) -> 5588.6785
A12: 2023 | B12: 17.31 | C12: 25.3 | D12: 0.15 | E12: 0.15 | F12: =(D12+E12)/B12 -> 0.017331023 | G12: =(C12-B12+D12+E12)/B12 -> 0.47891392 | H12: =H11*(1+G12) -> 8265.1744
A13: 2024 | B13: 25.11 | C13: 36.37 | D13: 0.15 | E13: 0.15 | F13: =(D13+E13)/B13 -> 0.011947431 | G13: =(C13-B13+D13+E13)/B13 -> 0.46037435 | H13: =H12*(1+G13) -> 12070.249

Sheet Retail Property
A1: Year | B1: Start of Year Price | C1: End of Year Price | D1: Divdends(the first half year) | E1: Divdends(the second half year) | F1: Income Yield % | G1: Total Return % | H1: Cumulative $ | I1: Notes
A2: 2013 | B2: 3.19 | C2: 2.97 | D2: 0.095 | E2: 0.0993 | F2: =(D2+E2)/B2 -> 0.060909091 | G2: =(C2-B2+D2+E2)/B2 -> -0.0080564263 | H2: =1000*(1+G2) -> 991.94357
A3: 2014 | B3: 2.99 | C3: 3.5 | D3: 0.0993 | E3: 0.102 | F3: =(D3+E3)/B3 -> 0.067324415 | G3: =(C3-B3+D3+E3)/B3 -> 0.23789298 | H3: =H2*(1+G3) -> 1227.92
A4: 2015 | B4: 3.85 | C4: 4.19 | D4: 0.102 | E4: 0.1045 | F4: =(D4+E4)/B4 -> 0.053636364 | G4: =(C4-B4+D4+E4)/B4 -> 0.14194805 | H4: =H3*(1+G4) -> 1402.2208
A5: 2016 | B5: 4.17 | C5: 4.64 | D5: 0.1045 | E5: 0.1065 | F5: =(D5+E5)/B5 -> 0.05059952 | G5: =(C5-B5+D5+E5)/B5 -> 0.16330935 | H5: =H4*(1+G5) -> 1631.2166
A6: 2017 | B6: 4.69 | C6: 4.19 | D6: 0.1065 | E6: 0.1086 | F6: =(D6+E6)/B6 -> 0.045863539 | G6: =(C6-B6+D6+E6)/B6 -> -0.060746269 | H6: =H5*(1+G6) -> 1532.1263
A7: 2018 | B7: 4.18 | C7: 3.9 | D7: 0.1087 | E7: 0.1108 | F7: =(D7+E7)/B7 -> 0.052511962 | G7: =(C7-B7+D7+E7)/B7 -> -0.014473684 | H7: =H6*(1+G7) -> 1509.9508
A8: 2019 | B8: 3.84 | C8: 3.83 | D8: 0.1108 | E8: 0.113 | F8: =(D8+E8)/B8 -> 0.05828125 | G8: =(C8-B8+D8+E8)/B8 -> 0.055677083 | H8: =H7*(1+G8) -> 1594.0204
A9: 2020 | B9: 3.85 | C9: 2.78 | D9: 0.113 | E9: 0 | F9: =(D9+E9)/B9 -> 0.029350649 | G9: =(C9-B9+D9+E9)/B9 -> -0.24857143 | H9: =H8*(1+G9) -> 1197.7925
A10: 2021 | B10: 2.78 | C10: 3.16 | D10: 0.07 | E10: 0.07 | F10: =(D10+E10)/B10 -> 0.050359712 | G10: =(C10-B10+D10+E10)/B10 -> 0.18705036 | H10: =H9*(1+G10) -> 1421.84
A11: 2022 | B11: 3.25 | C11: 2.88 | D11: 0.0725 | E11: 0.075 | F11: =(D11+E11)/B11 -> 0.045384615 | G11: =(C11-B11+D11+E11)/B11 -> -0.068461538 | H11: =H10*(1+G11) -> 1324.4987
A12: 2023 | B12: 2.88 | C12: 2.99 | D12: 0.0825 | E12: 0.0825 | F12: =(D12+E12)/B12 -> 0.057291667 | G12: =(C12-B12+D12+E12)/B12 -> 0.095486111 | H12: =H11*(1+G12) -> 1450.9699
A13: 2024 | B13: 3 | C13: 3.43 | D13: 0.0835 | E13: 0.086 | F13: =(D13+E13)/B13 -> 0.0565 | G13: =(C13-B13+D13+E13)/B13 -> 0.19983333 | H13: =H12*(1+G13) -> 1740.922

Sheet Logistics Facilities
A1: Year | B1: Start of Year Price | C1: End of Year Price | D1: Divdends(the first half year) | E1: Divdends(the second half year) | F1: Income Yield % | G1: Total Return % | H1: Cumulative $ | I1: Notes
A2: 2013 | B2: 3.27 | C2: 3.65 | D2: 0.098 | E2: 0.11 | F2: =(D2+E2)/B2 -> 0.063608563 | G2: =(C2-B2+D2+E2)/B2 -> 0.17981651 | H2: =1000*(1+G2) -> 1179.8165
A3: 2014 | B3: 3.68 | C3: 4.52 | D3: 0.113 | E3: 0.121 | F3: =(D3+E3)/B3 -> 0.063586957 | G3: =(C3-B3+D3+E3)/B3 -> 0.29184783 | H3: =H2*(1+G3) -> 1524.1434
A4: 2015 | B4: 4.57 | C4: 4.54 | D4: 0.121 | E4: 0.133 | F4: =(D4+E4)/B4 -> 0.055579869 | G4: =(C4-B4+D4+E4)/B4 -> 0.049015317 | H4: =H3*(1+G4) -> 1598.8498
A5: 2016 | B5: 4.51 | C5: 4.74 | D5: 0.136 | E5: 0.144 | F5: =(D5+E5)/B5 -> 0.062084257 | G5: =(C5-B5+D5+E5)/B5 -> 0.11308204 | H5: =H4*(1+G5) -> 1779.651
A6: 2017 | B6: 4.78 | C6: 6.02 | D6: 0.156 | E6: 0.165 | F6: =(D6+E6)/B6 -> 0.067154812 | G6: =(C6-B6+D6+E6)/B6 -> 0.32656904 | H6: =H5*(1+G6) -> 2360.8299
A7: 2018 | B7: 6.04 | C7: 7.42 | D7: 0.162 | E7: 0.165 | F7: =(D7+E7)/B7 -> 0.054139073 | G7: =(C7-B7+D7+E7)/B7 -> 0.28261589 | H7: =H6*(1+G7) -> 3028.0379
A8: 2019 | B8: 7.35 | C8: 11.08 | D8: 0.172 | E8: 0.175 | F8: =(D8+E8)/B8 -> 0.047210884 | G8: =(C8-B8+D8+E8)/B8 -> 0.55469388 | H8: =H7*(1+G8) -> 4707.672
A9: 2020 | B9: 11.14 | C9: 14.71 | D9: 0.1822 | E9: 0.1855 | F9: =(D9+E9)/B9 -> 0.033007181 | G9: =(C9-B9+D9+E9)/B9 -> 0.35347397 | H9: =H8*(1+G9) -> 6371.7115
A10: 2021 | B10: 15.11 | C10: 20.58 | D10: 0.1931 | E10: 0.1966 | F10: =(D10+E10)/B10 -> 0.025790867 | G10: =(C10-B10+D10+E10)/B10 -> 0.38780278 | H10: =H9*(1+G10) -> 8842.6789
A11: 2022 | B11: 20.9 | C11: 11.98 | D11: 0.2047 | E11: 0.2084 | F11: =(D11+E11)/B11 -> 0.01976555 | G11: =(C11-B11+D11+E11)/B11 -> -0.40702871 | H11: =H10*(1+G11) -> 5243.4548
A12: 2023 | B12: 11.86 | C12: 12.04 | D12: 0.217 | E12: 0.2209 | F12: =(D12+E12)/B12 -> 0.036922428 | G12: =(C12-B12+D12+E12)/B12 -> 0.052099494 | H12: =H11*(1+G12) -> 5516.6361
A13: 2024 | B13: 11.81 | C13: 14.35 | D13: 0.23 | E13: 0.2342 | F13: =(D13+E13)/B13 -> 0.039305673 | G13: =(C13-B13+D13+E13)/B13 -> 0.25437765 | H13: =H12*(1+G13) -> 6919.945

Sheet ASX 200
A1: Year | B1: Start of Year Price | C1: End of Year Price | D1: Income Yield % | E1: Total Return % | F1: Cumulative $ | G1: Notes
A2: 2013 | B2: 37702 | C2: 43065 | D2: 4.5 | E2: =(C2-B2)/B2 -> 0.1422471 | F2: =1000*(1+E2/100) -> 1001.4225 | G2: Dividend yield assumed at 4.5%, based on long-run ASX 200 average (S&P, 2023).
A3: 2014 | B3: 41761 | C3: 45352 | D3: 4.5 | E3: =(C3-B3)/B3 -> 0.08598932 | F3: =F2*(1+E3/100) -> 1002.2836 | G3: Initial investment assumed at $1,000 in line with assignment brief
A4: 2015 | B4: 46839 | C4: 46374 | D4: 4.5 | E4: =(C4-B4)/B4 -> -0.0099276244 | F4: =F3*(1+E4/100) -> 1002.1841
A5: 2016 | B5: 43833 | C5: 51683 | D5: 4.5 | E5: =(C5-B5)/B5 -> 0.17908881 | F5: =F4*(1+E5/100) -> 1003.9789
A6: 2017 | B6: 51275 | C6: 57607 | D6: 4.5 | E6: =(C6-B6)/B6 -> 0.12349098 | F6: =F5*(1+E6/100) -> 1005.2187
A7: 2018 | B7: 57348 | C7: 55804 | D7: 4.5 | E7: =(C7-B7)/B7 -> -0.026923345 | F7: =F6*(1+E7/100) -> 1004.9481
A8: 2019 | B8: 57963 | C8: 68651 | D8: 4.5 | E8: =(C8-B8)/B8 -> 0.18439349 | F8: =F7*(1+E8/100) -> 1006.8011
A9: 2020 | B9: 72073 | C9: 69463 | D9: 4.5 | E9: =(C9-B9)/B9 -> -0.036213284 | F9: =F8*(1+E9/100) -> 1006.4365
A10: 2021 | B10: 69679 | C10: 81253 | D10: 4.5 | E10: =(C10-B10)/B10 -> 0.16610457 | F10: =F9*(1+E10/100) -> 1008.1083
A11: 2022 | B11: 76092 | C11: 80182 | D11: 4.5 | E11: =(C11-B11)/B11 -> 0.053750723 | F11: =F10*(1+E11/100) -> 1008.6501
A12: 2023 | B12: 85173 | C12: 89937 | D12: 4.5 | E12: =(C12-B12)/B12 -> 0.055933218 | F12: =F11*(1+E12/100) -> 1009.2143
A13: 2024 | B13: 91004 | C13: 100010 | D13: 4.5 | E13: =(C13-B13)/B13 -> 0.098962683 | F13: =F12*(1+E13/100) -> 1010.2131

Sheet Gov Bonds
A1: Year | B1: Start of Year Price | C1: End of Year Price | D1: Income Yield % | E1: Total Return % | F1: Cumulative $ | G1: Notes
A2: 2013 | B2: 3.62 | C2: 4.44 | D2: 3.45 | E2: =D2/100 -> 0.0345 | F2: =1000*(1+E2) -> 1034.5 | G2: Income yield is approximated using the 10-year bond yield at the start of each year. The 'Close' value reflects the market rate an investor would receive.
A3: 2014 | B3: 4.41 | C3: 3.16 | D3: 4.03 | E3: =D3/100 -> 0.0403 | F3: =F2*(1+E3) -> 1076.1904 | G3: Total return approximated by income yield, assuming no capital gain/loss for government bonds
A4: 2015 | B4: 2.88 | C4: 2.98 | D4: 2.47 | E4: =D4/100 -> 0.0247 | F4: =F3*(1+E4) -> 1102.7723
A5: 2016 | B5: 2.9 | C5: 2.94 | D5: 2.67 | E5: =D5/100 -> 0.0267 | F5: =F4*(1+E5) -> 1132.2163
A6: 2017 | B6: 2.82 | C6: 2.73 | D6: 2.73 | E6: =D6/100 -> 0.0273 | F6: =F5*(1+E6) -> 1163.1258
A7: 2018 | B7: 2.89 | C7: 2.62 | D7: 2.8 | E7: =D7/100 -> 0.028 | F7: =F6*(1+E7) -> 1195.6933
A8: 2019 | B8: 2.39 | C8: 1.38 | D8: 2.23 | E8: =D8/100 -> 0.0223 | F8: =F7*(1+E8) -> 1222.3573
A9: 2020 | B9: 1.42 | C9: 1.08 | D9: 0.95 | E9: =D9/100 -> 0.0095 | F9: =F8*(1+E9) -> 1233.9697
A10: 2021 | B10: 1.11 | C10: 1.74 | D10: 1.09 | E10: =D10/100 -> 0.0109 | F10: =F9*(1+E10) -> 1247.4199
A11: 2022 | B11: 2.05 | C11: 4.09 | D11: 1.91 | E11: =D11/100 -> 0.0191 | F11: =F10*(1+E11) -> 1271.2456
A12: 2023 | B12: 4.06 | C12: 4.51 | D12: 3.52 | E12: =D12/100 -> 0.0352 | F12: =F11*(1+E12) -> 1315.9935
A13: 2024 | B13: 4.33 | C13: 4.51 | D13: 4.07 | E13: =D13/100 -> 0.0407 | F13: =F12*(1+E13) -> 1369.5544

Sheet Corp Bonds
A1: Year | B1: Start of Year Price | C1: End of Year Price | D1: Divdends | E1: Income Yield % | F1: Total Return % | G1: Cumulative $ | H1: Notes
A2: 2013 | B2: 102.5 | C2: 104 | D2: 3 | E2: =D2/B2 -> 0.029268293 | F2: =(C2-B2+D2)/B2 -> 0.043902439 | G2: =1000*(1+F2) -> 1043.9024
A3: 2014 | B3: 104 | C3: 106.5 | D3: 3.1 | E3: =D3/B3 -> 0.029807692 | F3: =(C3-B3+D3)/B3 -> 0.053846154 | G3: =G2*(1+F3) -> 1100.1126
A4: 2015 | B4: 106.5 | C4: 108 | D4: 3.2 | E4: =D4/B4 -> 0.030046948 | F4: =(C4-B4+D4)/B4 -> 0.044131455 | G4: =G3*(1+F4) -> 1148.6621
A5: 2016 | B5: 108 | C5: 110 | D5: 3.3 | E5: =D5/B5 -> 0.030555556 | F5: =(C5-B5+D5)/B5 -> 0.049074074 | G5: =G4*(1+F5) -> 1205.0317
A6: 2017 | B6: 110 | C6: 111.5 | D6: 3.4 | E6: =D6/B6 -> 0.030909091 | F6: =(C6-B6+D6)/B6 -> 0.044545455 | G6: =G5*(1+F6) -> 1258.7104
A7: 2018 | B7: 111.5 | C7: 112 | D7: 3.5 | E7: =D7/B7 -> 0.031390135 | F7: =(C7-B7+D7)/B7 -> 0.035874439 | G7: =G6*(1+F7) -> 1303.8659
A8: 2019 | B8: 112 | C8: 113.5 | D8: 3.6 | E8: =D8/B8 -> 0.032142857 | F8: =(C8-B8+D8)/B8 -> 0.045535714 | G8: =G7*(1+F8) -> 1363.2383
A9: 2020 | B9: 113.5 | C9: 114.5 | D9: 3.7 | E9: =D9/B9 -> 0.032599119 | F9: =(C9-B9+D9)/B9 -> 0.041409692 | G9: =G8*(1+F9) -> 1419.6896
A10: 2021 | B10: 114.5 | C10: 115.5 | D10: 3.8 | E10: =D10/B10 -> 0.033187773 | F10: =(C10-B10+D10)/B10 -> 0.041921397 | G10: =G9*(1+F10) -> 1479.205
A11: 2022 | B11: 115.5 | C11: 116 | D11: 3.9 | E11: =D11/B11 -> 0.033766234 | F11: =(C11-B11+D11)/B11 -> 0.038095238 | G11: =G10*(1+F11) -> 1535.5557
A12: 2023 | B12: 116 | C12: 117.5 | D12: 4 | E12: =D12/B12 -> 0.034482759 | F12: =(C12-B12+D12)/B12 -> 0.047413793 | G12: =G11*(1+F12) -> 1608.3622
A13: 2024 | B13: 117.05 | C13: 118 | D13: 4.1 | E13: =D13/B13 -> 0.035027766 | F13: =(C13-B13+D13)/B13 -> 0.043143956 | G13: =G12*(1+F13) -> 1677.7533

Sheet Gold (AUD)
A1: Year | B1: Start of Year Price | C1: End of Year Price | D1: Income Yield % | E1: Total Return % | F1: Cumulative $ | G1: Notes
A2: 2013 | B2: 1580.5 | C2: 1368.62 | D2: 0 | E2: =(C2-B2)/B2 -> -0.13405884 | F2: =1000*(1+E2) -> 865.94116 | G2: Income yield is 0% as gold is a non-yielding asset
A3: 2014 | B3: 1416.77 | C3: 1619.02 | D3: 0 | E3: =(C3-B3)/B3 -> 0.14275429 | F3: =F2*(1+E3) -> 989.55798
A4: 2015 | B4: 1628.65 | C4: 1541.97 | D4: 0 | E4: =(C4-B4)/B4 -> -0.053221994 | F4: =F3*(1+E4) -> 936.89173
A5: 2016 | B5: 1657.54 | C5: 1590.13 | D5: 0 | E5: =(C5-B5)/B5 -> -0.040668702 | F5: =F4*(1+E5) -> 898.78956
A6: 2017 | B6: 1628.65 | C6: 1599.76 | D6: 0 | E6: =(C6-B6)/B6 -> -0.017738618 | F6: =F5*(1+E6) -> 882.84627
A7: 2018 | B7: 1667.17 | C7: 1734.59 | D7: 0 | E7: =(C7-B7)/B7 -> 0.040439787 | F7: =F6*(1+E7) -> 918.54839
A8: 2019 | B8: 1792.38 | C8: 2235.4 | D8: 0 | E8: =(C8-B8)/B8 -> 0.24716857 | F8: =F7*(1+E8) -> 1145.5847
A9: 2020 | B9: 2235.4 | C9: 2456.91 | D9: 0 | E9: =(C9-B9)/B9 -> 0.099091885 | F9: =F8*(1+E9) -> 1259.1028
A10: 2021 | B10: 2447.28 | C10: 2495.43 | D10: 0 | E10: =(C10-B10)/B10 -> 0.019674904 | F10: =F9*(1+E10) -> 1283.8756
A11: 2022 | B11: 2553.22 | C11: 2659.16 | D11: 0 | E11: =(C11-B11)/B11 -> 0.041492703 | F11: =F10*(1+E11) -> 1337.147
A12: 2023 | B12: 2716.94 | C12: 3111.81 | D12: 0 | E12: =(C12-B12)/B12 -> 0.1453363 | F12: =F11*(1+E12) -> 1531.483
A13: 2024 | B13: 3131.07 | C13: 4277.15 | D13: 0 | E13: =(C13-B13)/B13 -> 0.36603461 | F13: =F12*(1+E13) -> 2092.0588

Sheet Iron Ore (AUD)
A1: Year | B1: Start of Year Price | C1: End of Year Price | D1: Income Yield % | E1: Total Return % | F1: Cumulative $ | G1: Notes
A2: 2013 | B2: 1.43 | C2: 1.51 | D2: 0 | E2: =(C2-B2)/B2 -> 0.055944056 | F2: =1000*(1+E2) -> 1055.9441 | G2: Iron ore is a non-income-producing commodity; income yield assumed to be 0%
A3: 2014 | B3: 1.44 | C3: 0.83 | D3: 0 | E3: =(C3-B3)/B3 -> -0.42361111 | F3: =F2*(1+E3) -> 608.63442
A4: 2015 | B4: 0.84 | C4: 0.56 | D4: 0 | E4: =(C4-B4)/B4 -> -0.33333333 | F4: =F3*(1+E4) -> 405.75628
A5: 2016 | B5: 0.6 | C5: 1.09 | D5: 0 | E5: =(C5-B5)/B5 -> 0.81666667 | F5: =F4*(1+E5) -> 737.12391
A6: 2017 | B6: 1.08 | C6: 0.95 | D6: 0 | E6: =(C6-B6)/B6 -> -0.12037037 | F6: =F5*(1+E6) -> 648.39603
A7: 2018 | B7: 0.96 | C7: 0.96 | D7: 0 | E7: =(C7-B7)/B7 -> 0 | F7: =F6*(1+E7) -> 648.39603
A8: 2019 | B8: 1.07 | C8: 1.35 | D8: 0 | E8: =(C8-B8)/B8 -> 0.26168224 | F8: =F7*(1+E8) -> 818.06976
A9: 2020 | B9: 1.39 | C9: 2.07 | D9: 0 | E9: =(C9-B9)/B9 -> 0.48920863 | F9: =F8*(1+E9) -> 1218.2765
A10: 2021 | B10: 2.2 | C10: 1.64 | D10: 0 | E10: =(C10-B10)/B10 -> -0.25454545 | F10: =F9*(1+E10) -> 908.16979
A11: 2022 | B11: 1.85 | C11: 1.66 | D11: 0 | E11: =(C11-B11)/B11 -> -0.1027027 | F11: =F10*(1+E11) -> 814.8983
A12: 2023 | B12: 1.76 | C12: 2.06 | D12: 0 | E12: =(C12-B12)/B12 -> 0.17045455 | F12: =F11*(1+E12) -> 953.80142
A13: 2024 | B13: 2.04 | C13: 1.54 | D13: 0 | E13: =(C13-B13)/B13 -> -0.24509804 | F13: =F12*(1+E13) -> 720.02656

Sheet Summary
A1: Asset Name | B1: Avg Return | C1: Std Dev | D1: Sharpe Ratio | E1: CAGR | F1: Category | G1: Notes
A2: Residential Property | B2: =AVERAGE('Residential Property'!E2:E13) -> 0.06765458 | C2: =_xlfn.STDEV.P('Residential Property'!E2:E13) -> 0.0076676814 | D2: =(B2-2.5%)/C2 -> 5.5629046 | E2: =('Residential Property'!F13/1000)^(1/12)-1 -> 0.067627064 | F2: Real Estate | G2: The 2.5% is the average RBA cash rate over the years — used as the risk-free rate for Sharpe Ratio.
A3: Commercial Office | B3: =AVERAGE('Commercial Office'!E2:E13) -> 0.051484459 | C3: =_xlfn.STDEV.P('Commercial Office'!F2:F13) -> 0.005577428 | D3: =(B3-2.5%)/C3 -> 4.7485076 | E3: =('Commercial Office'!G13/1000)^(1/12)-1 -> 0.084686825 | F3: Real Estate
A4: Inductrial Warehouse | B4: =AVERAGE('Industrial Warehouse'!G2:G13) -> 0.2554707 | C4: =_xlfn.STDEV.P('Industrial Warehouse'!G2:G13) -> 0.2224197 | D4: =(B4-2.5%)/C4 -> 1.0361973 | E4: =('Industrial Warehouse'!H13/1000)^(1/12)-1 -> 0.23067398 | F4: Real Estate
A5: Retail Property | B5: =AVERAGE('Retail Property'!G2:G13) -> 0.05674066 | C5: =_xlfn.STDEV.P('Retail Property'!G2:G13) -> 0.13612378 | D5: =(B5-2.5%)/C5 -> 0.23317498 | E5: =('Retail Property'!H13/1000)^(1/12)-1 -> 0.047285145 | F5: Real Estate
A6: Logistics Facilities | B6: =AVERAGE('Logistics Facilities'!G2:G13) -> 0.20319714 | C6: =_xlfn.STDEV.P('Logistics Facilities'!G2:G13) -> 0.2309156 | D6: =(B6-2.5%)/C6 -> 0.77169814 | E6: =('Logistics Facilities'!H13/1000)^(1/12)-1 -> 0.1749207 | F6: Real Estate
A7: ASX 200 | B7: =AVERAGE('ASX 200'!E2:E13) -> 0.084741387 | C7: =_xlfn.STDEV.P('ASX 200'!E2:E13) -> 0.075451852 | D7: =(B7-2.5%)/C7 -> 0.79178158 | E7: =('ASX 200'!F13/1000)^(1/12)-1 -> 0.00084712942 | F7: Other (Equity)
A8: Government Bonds | B8: =AVERAGE('Gov Bonds'!E2:E13) -> 0.0266 | C8: =_xlfn.STDEV.P('Gov Bonds'!E2:E13) -> 0.0097578174 | D8: =(B8-2.5%)/C8 -> 0.16397109 | E8: =('Gov Bonds'!F13/1000)^(1/12)-1 -> 0.026553547 | F8: Other (Fixed Income)
A9: Corporate Bonds | B9: =AVERAGE('Corp Bonds'!F2:F13) -> 0.044074484 | C9: =_xlfn.STDEV.P('Corp Bonds'!F2:F13) -> 0.0045608585 | D9: =(B9-2.5%)/C9 -> 4.1822135 | E9: =('Corp Bonds'!G13/1000)^(1/12)-1 -> 0.04406453 | F9: Other (Fixed Income)
A10: Gold (AUD) | B10: =AVERAGE('Gold (AUD)'!E2:E13) -> 0.071358742 | C10: =_xlfn.STDEV.P('Gold (AUD)'!E2:E13) -> 0.13285534 | D10: =(B10-2.5%)/C10 -> 0.34894149 | E10: =('Gold (AUD)'!F13/1000)^(1/12)-1 -> 0.063443671 | F10: Other (Commodity)
A11: Iron Ore (AUD) | B11: =AVERAGE('Iron Ore (AUD)'!E2:E13) -> 0.026191261 | C11: =_xlfn.STDEV.P('Iron Ore (AUD)'!E2:E13) -> 0.34630919 | D11: =(B11-2.5%)/C11 -> 0.0034398772 | E11: =('Iron Ore (AUD)'!F13/1000)^(1/12)-1 -> -0.027001039 | F11: Other (Commodity)
